remio/__init__.py
remio/camio.py
remio/httpservers.py
remio/mjpeg.py
remio/mockup.py
remio/network.py
remio/pool.py
remio/serialio.py
remio/sevent.py
remio/socketAsync.py
remio/socketSync.py
remio/stream.py
remio/timers.py
remio-0.1.2.dist-info/LICENSE
remio-0.1.2.dist-info/METADATA
remio-0.1.2.dist-info/WHEEL
remio-0.1.2.dist-info/top_level.txt
remio-0.1.2.dist-info/RECORD
