Metadata-Version: 2.1
Name: remio
Version: 0.1.2
Summary: A library for managing concurrent socketio, cv2, and pyserial processes. Useful for making robots or devices with Arduinos and Raspberry Pi.
Home-page: https://github.com/Hikki12/remio
Author: Jason Francisco Macas Mora
Author-email: franciscomacas3@gmail.com
License: Apache License 2.0
Project-URL: Bug Reports, https://github.com/Hikki12/remio/issues
Project-URL: Source, https://github.com/Hikki12/remio
Project-URL: Documentation, https://hikki12.github.io/remio
Keywords: OpenCV,Serial,SocketIO,multithreading,multiprocessing,IoT,mjpeg,Arduino
Classifier: Development Status :: 5 - Production/Stable
Classifier: Operating System :: POSIX
Classifier: Operating System :: MacOS :: MacOS X
Classifier: Topic :: Multimedia :: Video
Classifier: Topic :: Scientific/Engineering
Classifier: Intended Audience :: Developers
Classifier: Intended Audience :: Science/Research
Classifier: Intended Audience :: Education
Classifier: License :: OSI Approved :: Apache Software License
Classifier: Programming Language :: Python :: 3.7
Classifier: Programming Language :: Python :: 3.8
Classifier: Programming Language :: Python :: 3.9
Requires-Python: >=3.7
License-File: LICENSE
Requires-Dist: opencv-python (>=4.5.4.60)
Requires-Dist: pyserial (>=3.5)
Requires-Dist: python-socketio (>=4.6.1)
Requires-Dist: websocket-client (==1.3.2)
Requires-Dist: requests (>=2.27.0)
Requires-Dist: simplejpeg (>=1.6.3)
Requires-Dist: python-decouple (==3.6)
Requires-Dist: netifaces (>=0.11.0)
